Metadata-Version: 2.1
Name: dsnd-probability-alela
Version: 1.2
Summary: Gaussian and binomial distributions
Home-page: UNKNOWN
Author: Alela
Author-email: alelasantillan@gmail.com
License: UNKNOWN
Platform: UNKNOWN
